{
  "704f463ce10e4c6c96ce1073fb18e0e6": {
    "contentType": "text/html",
    "id": "704f463ce10e4c6c96ce1073fb18e0e6",
    "shared": "false",
    "visibleToAuthenticatedUsers": false,
    "visibleToPublicUsers": false
  },
  "9e071a2b50514a779a942eda30178cbe": {
    "contentType": "text/html",
    "id": "9e071a2b50514a779a942eda30178cbe",
    "shared": "false",
    "visibleToAuthenticatedUsers": false,
    "visibleToPublicUsers": false
  },
  "Main Page Template-fc86242194c44060a7fac0d1804df054": {
    "contentType": "text/html",
    "id": "fc86242194c44060a7fac0d1804df054",
    "shared": "true",
    "visibleToAuthenticatedUsers": false,
    "visibleToPublicUsers": false
  }
}